gmp.cpython-314t-x86_64-linux-gnu.so
libzz.so
python_gmp.libs/libgmp-466f8e8e.so.10.5.0
python_gmp-0.4.0.dist-info/METADATA
python_gmp-0.4.0.dist-info/WHEEL
python_gmp-0.4.0.dist-info/RECORD
python_gmp-0.4.0.dist-info/licenses/LICENSE
