Metadata-Version: 2.4
Name: python-gmp
Version: 0.4.0
Summary: Safe bindings to the GNU GMP library
Keywords: gmp,multiple-precision,arbitrary-precision,bignum
Author-Email: Sergey B Kirpichev <skirpichev@gmail.com>
Maintainer-Email: Sergey B Kirpichev <skirpichev@gmail.com>
License-Expression: MIT
License-File: LICENSE
Classifier: Development Status :: 4 - Beta
Classifier: Intended Audience :: Developers
Classifier: Intended Audience :: Science/Research
Classifier: Natural Language :: English
Classifier: Operating System :: POSIX
Classifier: Programming Language :: C
Classifier: Programming Language :: Python :: 3
Classifier: Programming Language :: Python :: 3 :: Only
Classifier: Programming Language :: Python :: 3.9
Classifier: Programming Language :: Python :: 3.10
Classifier: Programming Language :: Python :: 3.11
Classifier: Programming Language :: Python :: 3.12
Classifier: Programming Language :: Python :: 3.13
Classifier: Programming Language :: Python :: 3.14
Classifier: Programming Language :: Python :: Free Threading :: 2 - Beta
Classifier: Programming Language :: Python :: Implementation :: CPython
Classifier: Programming Language :: Python :: Implementation :: PyPy
Classifier: Programming Language :: Python :: Implementation :: GraalPy
Classifier: Operating System :: Microsoft :: Windows
Classifier: Operating System :: POSIX
Classifier: Operating System :: Unix
Classifier: Operating System :: MacOS
Classifier: Topic :: Scientific/Engineering :: Mathematics
Classifier: Topic :: Software Development :: Libraries :: Python Modules
Project-URL: Homepage, https://github.com/diofant/python-gmp
Project-URL: Source Code, https://github.com/diofant/python-gmp
Project-URL: Bug Tracker, https://github.com/diofant/python-gmp/issues
Project-URL: Documentation, https://python-gmp.readthedocs.io/en/latest/
Requires-Python: >=3.9
Provides-Extra: tests
Requires-Dist: pytest; extra == "tests"
Requires-Dist: hypothesis; extra == "tests"
Requires-Dist: mpmath>=1.4.0a7; extra == "tests"
Provides-Extra: docs
Requires-Dist: sphinx>=8.2; extra == "docs"
Provides-Extra: develop
Requires-Dist: python-gmp[docs,tests]; extra == "develop"
Requires-Dist: pre-commit; extra == "develop"
Requires-Dist: pyperf; extra == "develop"
